torchanalyzer/__init__.py
torchanalyzer/base.py
torchanalyzer/flops.py
torchanalyzer/flops_kernel.py
torchanalyzer/in_out.py
torchanalyzer/memops_kernel.py
torchanalyzer/op_tree.py
torchanalyzer/time_mem.py
torchanalyzer/utils.py
torchanalyzer/viser.py
torch_analyzer-1.4.2.dist-info/LICENSE
torch_analyzer-1.4.2.dist-info/METADATA
torch_analyzer-1.4.2.dist-info/WHEEL
torch_analyzer-1.4.2.dist-info/top_level.txt
torch_analyzer-1.4.2.dist-info/RECORD
