Metadata-Version: 2.1
Name: torch-analyzer
Version: 1.4.2
Summary: A torch model analyzer
Home-page: https://github.com/IrisRainbowNeko/torch-analyzer
Author: Ziyi Dong
Author-email: dzy7eu7d7@gmail.com
Classifier: License :: OSI Approved :: Apache Software License
Classifier: Operating System :: OS Independent
Classifier: Programming Language :: Python :: 3
Classifier: Programming Language :: Python :: 3.7
Classifier: Programming Language :: Python :: 3.8
Classifier: Programming Language :: Python :: 3.9
Classifier: Programming Language :: Python :: 3.10
Classifier: Topic :: Scientific/Engineering :: Artificial Intelligence
Requires-Python: >=3.7
License-File: LICENSE
Requires-Dist: numpy
Requires-Dist: prettytable
